flexidot/__init__.py
flexidot/_version.py
flexidot/app.py
flexidot/plotting.py
flexidot/utils/alphabets.py
flexidot/utils/analysis.py
flexidot/utils/args.py
flexidot/utils/checks.py
flexidot/utils/file_handling.py
flexidot/utils/logs.py
flexidot/utils/matching.py
flexidot/utils/utils.py
flexidot-2.0.2.dist-info/METADATA
flexidot-2.0.2.dist-info/WHEEL
flexidot-2.0.2.dist-info/entry_points.txt
flexidot-2.0.2.dist-info/licenses/LICENSE
flexidot-2.0.2.dist-info/RECORD
