Metadata-Version: 2.4
Name: flexidot
Version: 2.0.2
Summary: Flexible dotplotting of genomic sequences.
Project-URL: homepage, https://github.com/flexidot-bio/flexidot
Project-URL: documentation, https://github.com/flexidot-bio/flexidot
Project-URL: repository, https://github.com/flexidot-bio/flexidot
Author: Kathrin M. Seibt, Thomas Schmidt, Tony Heitkam
License: GNU Lesser General Public License v3 (LGPLv3)
License-File: LICENSE
Classifier: Intended Audience :: Science/Research
Classifier: License :: OSI Approved :: GNU Lesser General Public License v3 (LGPLv3)
Classifier: Programming Language :: Python :: 3
Classifier: Topic :: Scientific/Engineering :: Bio-Informatics
Requires-Python: >=3.8
Requires-Dist: biopython
Requires-Dist: colormap>=1.3.0
Requires-Dist: colour
Requires-Dist: easydev
Requires-Dist: matplotlib
Requires-Dist: numpy
Requires-Dist: regex
Requires-Dist: rich
Provides-Extra: dev
Requires-Dist: hatch; extra == 'dev'
Requires-Dist: isort; extra == 'dev'
Requires-Dist: mkdocs; extra == 'dev'
Requires-Dist: mkdocs-jupyter; extra == 'dev'
Requires-Dist: mkdocs-material; extra == 'dev'
Requires-Dist: mkdocstrings; extra == 'dev'
Requires-Dist: mkdocstrings-python; extra == 'dev'
Requires-Dist: notebook; extra == 'dev'
Requires-Dist: numpydoc-validation; extra == 'dev'
Requires-Dist: pre-commit; extra == 'dev'
Requires-Dist: pymdown-extensions; extra == 'dev'
Requires-Dist: pytest; extra == 'dev'
Requires-Dist: pytest-cov; extra == 'dev'
Requires-Dist: ruff; extra == 'dev'
Requires-Dist: seaborn; extra == 'dev'
Provides-Extra: tests
Requires-Dist: hatch; extra == 'tests'
Requires-Dist: pytest; extra == 'tests'
Requires-Dist: pytest-cov; extra == 'tests'
